Metadata-Version: 2.1
Name: regression-model-template
Version: 0.1.0
Summary: Example regression model package for house prices.
Home-page: https://github.com/particle1331/model-deployment
Author: particle1331
Author-email: particle1331@gmail.com
License: BSD-3
Platform: UNKNOWN
Classifier: License :: OSI Approved :: MIT License
Classifier: Programming Language :: Python
Classifier: Programming Language :: Python :: 3
Classifier: Programming Language :: Python :: 3.6
Classifier: Programming Language :: Python :: 3.7
Classifier: Programming Language :: Python :: 3.8
Classifier: Programming Language :: Python :: 3.9
Classifier: Programming Language :: Python :: Implementation :: CPython
Classifier: Programming Language :: Python :: Implementation :: PyPy
Requires-Python: >=3.6.0
Requires-Dist: numpy (<1.23.0,>=1.22.0)
Requires-Dist: pandas (<1.5.0,>=1.4.0)
Requires-Dist: pydantic (<1.9.0,>=1.8.1)
Requires-Dist: pandera (>=0.9.0<1.0.0)
Requires-Dist: scikit-learn (<1.1.0,>=1.0.0)
Requires-Dist: strictyaml (<1.4.0,>=1.3.2)
Requires-Dist: ruamel.yaml (==0.16.12)
Requires-Dist: feature-engine (<1.1.0,>=1.0.2)
Requires-Dist: joblib (<1.1.0,>=1.0.1)
